sql_cc_sync/__init__.py
sql_cc_sync/cc_wellheader.py
sql_cc_sync/main.py
sql_cc_sync/types.py
sql_cc_sync-1.0.82.dist-info/METADATA
sql_cc_sync-1.0.82.dist-info/WHEEL
sql_cc_sync-1.0.82.dist-info/entry_points.txt
sql_cc_sync-1.0.82.dist-info/top_level.txt
sql_cc_sync-1.0.82.dist-info/RECORD
