Metadata-Version: 2.2
Name: sql-cc-sync
Version: 1.0.82
Summary: SQL <-> CC synchronization interface
Home-page: https://gitlab.com/gryphonog/eiv/cc_api_scripts
Author: ['David S. Fulford']
Author-email: ['dfulford@eivcapital.com']
Requires-Dist: combocurve-api-helper>=1.1.6
Requires-Dist: pandas>=2.0
Requires-Dist: percival>=1.2.0
Requires-Dist: rich
Dynamic: author
Dynamic: author-email
Dynamic: description
Dynamic: description-content-type
Dynamic: home-page
Dynamic: requires-dist
Dynamic: summary
